langchain_zhipuai_dev/__init__.py
langchain_zhipuai_dev/chat.py
langchain_zhipuai_dev/embedding.py
langchain_zhipuai_dev-0.3.0.dist-info/METADATA
langchain_zhipuai_dev-0.3.0.dist-info/WHEEL
langchain_zhipuai_dev-0.3.0.dist-info/licenses/LICENSE
langchain_zhipuai_dev-0.3.0.dist-info/RECORD
