Metadata-Version: 2.4
Name: langchain-zhipuai-dev
Version: 0.3.0
Summary: Implementation of LangChain for ZhipuAI(Just for coding exercise)
Author-email: poneding <poneding@gmail.com>
License-File: LICENSE
Requires-Python: >=3.12
Requires-Dist: langchain-core>=0.3.62
Requires-Dist: zhipuai>=2.1.5.20250526
